{"cameraMode":{"drawMode":0,"name":"Shaded","section":"Shading Mode"},"sceneLighting":false,"audioPlay":false,"sceneViewState":{"m_AlwaysRefresh":false,"showFog":true,"showSkybox":false,"showFlares":true,"showImageEffects":true,"showParticleSystems":true,"showVisualEffectGraphs":true,"m_FxEnabled":true},"in2DMode":false,"pivot":{"x":0.0,"y":0.025000005960464479,"z":5.0},"rotation":{"x":-0.08319035172462464,"y":-0.051705263555049899,"z":0.004320359788835049,"w":-0.9951945543289185},"size":0.8863831758499146,"orthographic":true}